lenlp-1.2.0.dist-info/METADATA
lenlp-1.2.0.dist-info/WHEEL
lenlp/__init__.py
lenlp/_rslenlp.cpython-39-aarch64-linux-gnu.so
lenlp/analyzer/__init__.py
lenlp/analyzer/analyze.py
lenlp/counter/__init__.py
lenlp/counter/count.py
lenlp/flash/__init__.py
lenlp/flash/flash_text.py
lenlp/normalizer/__init__.py
lenlp/normalizer/normalize.py
lenlp/sparse/__init__.py
lenlp/sparse/bm25_vectorizer.py
lenlp/sparse/count_vectorizer.py
lenlp/sparse/tfidf_vectorizer.py
lenlp-1.2.0.dist-info/RECORD
