Metadata-Version: 2.4
Name: lenlp
Version: 1.2.0
Classifier: Programming Language :: Python :: 3
Classifier: Programming Language :: Rust
Classifier: Operating System :: OS Independent
Requires-Dist: scikit-learn>=1.5.0
Requires-Dist: scipy>=1.13.1
Requires-Dist: maturin>=1.5.1 ; extra == 'dev'
Requires-Dist: pytest-cov>=5.0.0 ; extra == 'dev'
Requires-Dist: pytest>=7.4.4 ; extra == 'dev'
Requires-Dist: ruff>=0.1.15 ; extra == 'dev'
Provides-Extra: dev
Summary: Natural Language Processing library for Python from Rust.
Keywords: 
Author-email: Raphael Sourty <raphael.sourty@gmail.com>
Requires-Python: >=3.8
Project-URL: Homepage, https://github.com/raphaelsty/lenlp
Project-URL: Documentation, https://github.com/raphaelsty/lenlp
Project-URL: Repository, https://github.com/raphaelsty/lenlp
